Workbook

Sheet TCS Data
B1: TCS Financial Data
B3: Particulars | C3: FY23 | D3: FY24 | E3: FY25 | G3: Variance Abs. FY23-24 | H3: Variance % FY23-24 | I3: Variance Abs. FY24-25 | J3: Variance % FY24-25
B4: Sales / Revenue | C4: 225458 | D4: 240893 | E4: 255324 | G4: =D4-C4 -> 15435 | H4: =G4/C4 -> 0.068460645 | I4: =E4-D4 -> 14431 | J4: =I4/D4 -> 0.059906265
B5: Expenses | C5: 166199 | D5: 176597 | E5: 187917 | G5: =D5-C5 -> 10398 | H5: =G5/C5 -> 0.062563553 | I5: =E5-D5 -> 11320 | J5: =I5/D5 -> 0.064100749
B6: Operating Profit | C6: 59259 | D6: 64296 | E6: 67407 | G6: =D6-C6 -> 5037 | H6: =G6/C6 -> 0.084999747 | I6: =E6-D6 -> 3111 | J6: =I6/D6 -> 0.048385592
B7: Net Profit | C7: 42147 | D7: 45908 | E7: 48553 | G7: =D7-C7 -> 3761 | H7: =G7/C7 -> 0.089235296 | I7: =E7-D7 -> 2645 | J7: =I7/D7 -> 0.05761523
B8: Tax | C8: 14604 | D8: 15898 | E8: 16534 | G8: =D8-C8 -> 1294 | H8: =G8/C8 -> 0.088605861 | I8: =E8-D8 -> 636 | J8: =I8/D8 -> 0.040005032
B9: Interest | C9: 779 | D9: 778 | E9: 796 | G9: =D9-C9 -> -1 | H9: =G9/C9 -> -0.001283697 | I9: =E9-D9 -> 18 | J9: =I9/D9 -> 0.023136247
B10: Depreciation | C10: 5022 | D10: 4985 | E10: 5242 | G10: =D10-C10 -> -37 | H10: =G10/C10 -> -0.0073675826 | I10: =E10-D10 -> 257 | J10: =I10/D10 -> 0.051554664
B12: Total Assets | C12: 142859 | D12: 145472 | E12: 158649 | G12: =D12-C12 -> 2613 | H12: =G12/C12 -> 0.018290762 | I12: =E12-D12 -> 13177 | J12: =I12/D12 -> 0.090581005
B13: Total Equity (Reserves + Share Capital) | C13: 90424 | D13: 90489 | E13: 94756 | G13: =D13-C13 -> 65 | H13: =G13/C13 -> 0.00071883571 | I13: =E13-D13 -> 4267 | J13: =I13/D13 -> 0.047154903
B14: Total Borrowings | C14: 7688 | D14: 8021 | E14: 9392 | G14: =D14-C14 -> 333 | H14: =G14/C14 -> 0.043314256 | I14: =E14-D14 -> 1371 | J14: =I14/D14 -> 0.17092632
B15: Current Assets(Other Assets) | C15: 83947 | D15: 92542 | E15: 103086 | G15: =D15-C15 -> 8595 | H15: =G15/C15 -> 0.10238603 | I15: =E15-D15 -> 10544 | J15: =I15/D15 -> 0.11393746
B16: Current Liabilities | C16: 44747 | D16: 46962 | E16: 54501 | G16: =D16-C16 -> 2215 | H16: =G16/C16 -> 0.049500525 | I16: =E16-D16 -> 7539 | J16: =I16/D16 -> 0.16053405
... B18: Debtors | C18: 49954 | D18: 53577 | E18: 59046 | G18: =D18-C18 -> 3623 | H18: =G18/C18 -> 0.072526725 | I18: =E18-D18 -> 5469 | J18: =I18/D18 -> 0.10207738
B20: Return on Equity (ROE) % | C20: 0.46610413 | D20: 0.50733238 | E20: 0.51240027
B21: Return on Capital Employed (ROCE) % | C21: 0.591442 | D21: 0.63853485 | E21: 0.65259699

Sheet Infosys Data
B1: Infosys Financial Data
B3: Particulars | C3: FY23 | D3: FY24 | E3: FY25 | G3: Variance Abs. FY23-24 | H3: Variance % FY23-24 | I3: Variance Abs. FY24-25 | J3: Variance % FY24-25
B4: Sales / Revenue | C4: 146767 | D4: 153670 | E4: 162990 | G4: =D4-C4 -> 6903 | H4: =G4/C4 -> 0.047033734 | I4: =E4-D4 -> 9320 | J4: =I4/D4 -> 0.060649444
B5: Expenses | C5: 111637 | D5: 117245 | E5: 123754 | G5: =D5-C5 -> 5608 | H5: =G5/C5 -> 0.050234241 | I5: =E5-D5 -> 6509 | J5: =I5/D5 -> 0.055516227
B6: Operating Profit | C6: 35130 | D6: 36425 | E6: 39236 | G6: =D6-C6 -> 1295 | H6: =G6/C6 -> 0.03686308 | I6: =E6-D6 -> 2811 | J6: =I6/D6 -> 0.077172272
B7: Net Profit | C7: 24095 | D7: 26233 | E7: 26713 | G7: =D7-C7 -> 2138 | H7: =G7/C7 -> 0.088732102 | I7: =E7-D7 -> 480 | J7: =I7/D7 -> 0.018297564
B8: Tax | C8: 9214 | D8: 9740 | E8: 10858 | G8: =D8-C8 -> 526 | H8: =G8/C8 -> 0.057087041 | I8: =E8-D8 -> 1118 | J8: =I8/D8 -> 0.11478439
B9: Interest | C9: 284 | D9: 470 | E9: 416 | G9: =D9-C9 -> 186 | H9: =G9/C9 -> 0.65492958 | I9: =E9-D9 -> -54 | J9: =I9/D9 -> -0.11489362
B10: Depreciation | C10: 4225 | D10: 4678 | E10: 4812 | G10: =D10-C10 -> 453 | H10: =G10/C10 -> 0.10721893 | I10: =E10-D10 -> 134 | J10: =I10/D10 -> 0.02864472
B12: Total Assets | C12: 124596 | D12: 137360 | E12: 147795 | G12: =D12-C12 -> 12764 | H12: =G12/C12 -> 0.1024431 | I12: =E12-D12 -> 10435 | J12: =I12/D12 -> 0.075968259
B13: Total Equity (Reserves + Share Capital) | C13: 75407 | D13: 88116 | E13: 95818 | G13: =D13-C13 -> 12709 | H13: =G13/C13 -> 0.16853873 | I13: =E13-D13 -> 7702 | J13: =I13/D13 -> 0.087407508
B14: Total Borrowings | C14: 8299 | D14: 8359 | E14: 8227 | G14: =D14-C14 -> 60 | H14: =G14/C14 -> 0.0072297867 | I14: =E14-D14 -> -132 | J14: =I14/D14 -> -0.015791363
B15: Current Assets(Other Assets) | C15: 75605 | D15: 84822 | E15: 92479 | G15: =D15-C15 -> 9217 | H15: =G15/C15 -> 0.12190993 | I15: =E15-D15 -> 7657 | J15: =I15/D15 -> 0.090271392
B16: Current Liabilities | C16: 40890 | D16: 40885 | E16: 43750 | G16: =D16-C16 -> -5 | H16: =G16/C16 -> -0.00012227929 | I16: =E16-D16 -> 2865 | J16: =I16/D16 -> 0.070074599
B17: Inventory | C17: 0 | D17: 0 | E17: 0 | G17: =D17-C17 -> 0 | H17: - | I17: =E17-D17 -> 0 | J17: -
B18: Debtors | C18: 25424 | D18: 30193 | E18: 31158 | G18: =D18-C18 -> 4769 | H18: =G18/C18 -> 0.18757867 | I18: =E18-D18 -> 965 | J18: =I18/D18 -> 0.031961051
B20: Return on Equity (ROE) % | C20: 0.31953267 | D20: 0.29770984 | E20: 0.27878895
B21: Return on Capital Employed (ROCE) % | C21: 0.40850909 | D21: 0.40468196 | E21: 0.37925394

Sheet Ratio Calculations
B1: Ratio Analysis
B3: RATIOS | D3: TCS | H3: Infosys
D4: FY23 | E4: FY24 | F4: FY25 | H4: FY23 | I4: FY24 | J4: FY25
B5: PROFITABILITY RATIOS
B6: Operating Profit Margin% | D6: ='TCS Data'!C6/'TCS Data'!C4 -> 0.26283831 | E6: ='TCS Data'!D6/'TCS Data'!D4 -> 0.26690688 | F6: ='TCS Data'!E6/'TCS Data'!E4 -> 0.26400573 | H6: ='Infosys Data'!C6/'Infosys Data'!C4 -> 0.23935898 | I6: ='Infosys Data'!D6/'Infosys Data'!D4 -> 0.2370339 | J6: ='Infosys Data'!E6/'Infosys Data'!E4 -> 0.24072642
B7: Net Profit Margin % | D7: ='TCS Data'!C7/'TCS Data'!C4 -> 0.18693947 | E7: ='TCS Data'!D7/'TCS Data'!D4 -> 0.19057424 | F7: ='TCS Data'!E7/'TCS Data'!E4 -> 0.1901623 | H7: ='Infosys Data'!C7/'Infosys Data'!C4 -> 0.16417178 | I7: ='Infosys Data'!D7/'Infosys Data'!D4 -> 0.17070996 | J7: ='Infosys Data'!E7/'Infosys Data'!E4 -> 0.16389349
B8: Return on Equity (ROE) % | D8: ='TCS Data'!C7/'TCS Data'!C13 -> 0.46610413 | E8: ='TCS Data'!D7/'TCS Data'!D13 -> 0.50733238 | F8: ='TCS Data'!E7/'TCS Data'!E13 -> 0.51240027 | H8: ='Infosys Data'!C7/'Infosys Data'!C13 -> 0.31953267 | I8: ='Infosys Data'!D7/'Infosys Data'!D13 -> 0.29770984 | J8: ='Infosys Data'!E7/'Infosys Data'!E13 -> 0.27878895
B9: Return on Assets (ROA) % | D9: ='TCS Data'!C7/'TCS Data'!C12 -> 0.29502516 | E9: ='TCS Data'!D7/'TCS Data'!D12 -> 0.31557963 | F9: ='TCS Data'!E7/'TCS Data'!E12 -> 0.30604038 | H9: ='Infosys Data'!C7/'Infosys Data'!C12 -> 0.19338502 | I9: ='Infosys Data'!D7/'Infosys Data'!D12 -> 0.19097991 | J9: ='Infosys Data'!E7/'Infosys Data'!E12 -> 0.1807436
B10: Return on Capital Employed (ROCE) % | D10: ='TCS Data'!C21 -> 0.591442 | E10: ='TCS Data'!D21 -> 0.63853485 | F10: ='TCS Data'!E21 -> 0.65259699 | H10: ='Infosys Data'!C21 -> 0.40850909 | I10: ='Infosys Data'!D21 -> 0.40468196 | J10: ='Infosys Data'!E21 -> 0.37925394
B11: EBITDA Margin % | D11: =('TCS Data'!C6+'TCS Data'!C10)/'TCS Data'!C4 -> 0.28511297 | E11: =('TCS Data'!D6+'TCS Data'!D10)/'TCS Data'!D4 -> 0.28760072 | F11: =('TCS Data'!E6+'TCS Data'!E10)/'TCS Data'!E4 -> 0.28453651 | H11: =('Infosys Data'!C6+'Infosys Data'!C10)/'Infosys Data'!C4 -> 0.26814611 | I11: =('Infosys Data'!D6+'Infosys Data'!D10)/'Infosys Data'!D4 -> 0.26747576 | J11: =('Infosys Data'!E6+'Infosys Data'!E10)/'Infosys Data'!E4 -> 0.27024971
B13: LIQUIDITY RATIOS
B14: Current Ratio | D14: =('TCS Data'!C15)/'TCS Data'!C16 -> 1.8760364 | E14: ='TCS Data'!D15/'TCS Data'!D16 -> 1.970572 | F14: ='TCS Data'!E15/'TCS Data'!E16 -> 1.8914515 | H14: ='Infosys Data'!C15/'Infosys Data'!C16 -> 1.8489851 | I14: ='Infosys Data'!D15/'Infosys Data'!D16 -> 2.0746484 | J14: ='Infosys Data'!E15/'Infosys Data'!E16 -> 2.1138057
B15: Quick Ratio | D15: =('TCS Data'!C15-'TCS Data'!C17)/'TCS Data'!C16 -> 1.8754106 | E15: =('TCS Data'!D15-'TCS Data'!D17)/'TCS Data'!D16 -> 1.9699757 | F15: =('TCS Data'!E15-'TCS Data'!E17)/'TCS Data'!E16 -> 1.8910662 | H15: =('Infosys Data'!C15-'Infosys Data'!C17)/'Infosys Data'!C16 -> 1.8489851 | I15: =('Infosys Data'!D15-'Infosys Data'!D17)/'Infosys Data'!D16 -> 2.0746484 | J15: =('Infosys Data'!E15-'Infosys Data'!E17)/'Infosys Data'!E16 -> 2.1138057
B17: EFFICIENCY RATIOS
B18: Asset Turnover Ratio | D18: ='TCS Data'!C4/'TCS Data'!C12 -> 1.5781855 | E18: ='TCS Data'!D4/'TCS Data'!D12 -> 1.6559407 | F18: ='TCS Data'!E4/'TCS Data'!E12 -> 1.6093641 | H18: ='Infosys Data'!C4/'Infosys Data'!C12 -> 1.1779431 | I18: ='Infosys Data'!D4/'Infosys Data'!D12 -> 1.1187391 | J18: ='Infosys Data'!E4/'Infosys Data'!E12 -> 1.1028113
B19: Debtor Days | D19: ='TCS Data'!C18/'TCS Data'!C4*360 -> 79.764036 | E19: ='TCS Data'!D18/'TCS Data'!D4*360 -> 80.067582 | F19: ='TCS Data'!E18/'TCS Data'!E4*360 -> 83.253278 | H19: ='Infosys Data'!C18/'Infosys Data'!C4*360 -> 62.361703 | I19: ='Infosys Data'!D18/'Infosys Data'!D4*360 -> 70.732609 | J19: ='Infosys Data'!E18/'Infosys Data'!E4*360 -> 68.819437
B21: SOLVENCY RATIOS
B22: Debt to Equity Ratio | D22: ='TCS Data'!C14/'TCS Data'!C13 -> 0.085021676 | E22: ='TCS Data'!D14/'TCS Data'!D13 -> 0.088640608 | F22: ='TCS Data'!E14/'TCS Data'!E13 -> 0.099117734 | H22: ='Infosys Data'!C14/'Infosys Data'!C13 -> 0.1100561 | I22: ='Infosys Data'!D14/'Infosys Data'!D13 -> 0.094863589 | J22: ='Infosys Data'!E14/'Infosys Data'!E13 -> 0.085860694
B23: Interest Coverage Ratio | D23: ='TCS Data'!C6/'TCS Data'!C9 -> 76.070603 | E23: ='TCS Data'!D6/'TCS Data'!D9 -> 82.642674 | F23: ='TCS Data'!E6/'TCS Data'!E9 -> 84.682161 | H23: ='Infosys Data'!C6/'Infosys Data'!C9 -> 123.69718 | I23: ='Infosys Data'!D6/'Infosys Data'!D9 -> 77.5 | J23: ='Infosys Data'!E6/'Infosys Data'!E9 -> 94.317308

Sheet Chart Data Sheet
B1: Chart Data Sheet
C3: Current Ratios | G3: Return on Equity (ROE) %
C4: Year | D4: TCS | E4: Infosys | G4: Year | H4: TCS | I4: Infosys
C5: FY23 | D5: 1.8760364 | E5: 1.8489851 | G5: FY23 | H5: 0.46610413 | I5: 0.31953267
C6: FY24 | D6: 1.970572 | E6: 2.0746484 | G6: FY24 | H6: 0.50733238 | I6: 0.29770984
C7: FY25 | D7: 1.8914515 | E7: 2.1138057 | G7: FY25 | H7: 0.51240027 | I7: 0.27878895
C11: Debt-Equity Ratios | G11: EBITDA Margin %
C12: Year | D12: TCS | E12: Infosys | G12: Year | H12: TCS | I12: Infosys
C13: FY23 | D13: 0.085021676 | E13: 0.1100561 | G13: FY23 | H13: 0.28511297 | I13: 0.26814611
C14: FY24 | D14: 0.088640608 | E14: 0.094863589 | G14: FY24 | H14: 0.28760072 | I14: 0.26747576
C15: FY25 | D15: 0.099117734 | E15: 0.085860694 | G15: FY25 | H15: 0.28453651 | I15: 0.27024971
C18: Net Profit Margin % | G18: Interest Coverage Ratio
C19: Year | D19: TCS | E19: Infosys | G19: Year | H19: TCS | I19: Infosys
C20: FY23 | D20: 0.18693947 | E20: 0.16417178 | G20: FY23 | H20: 76.070603 | I20: 123.69718
C21: FY24 | D21: 0.19057424 | E21: 0.17070996 | G21: FY24 | H21: 82.642674 | I21: 77.5
C22: FY25 | D22: 0.1901623 | E22: 0.16389349 | G22: FY25 | H22: 84.682161 | I22: 94.317308

Sheet Charts
B1: TCS vs Infosys — Financial Performance Analysis FY23–FY25

Sheet Insights
B1: Insights & Summary
B3: TCS vs Infosys — Financial Statement Analysis
B4: Comparative Ratio Analysis | FY2023 – FY2025
B6: 01 | Project Overview
B7: Objective
B8: This project conducts a comparative financial statement analysis of TCS (Tata Consultancy Services) and Infosys — two of India's largest IT companies — over FY2023 to FY2025. The objective is to evaluate and compare their financial health across profitability, liquidity, efficiency and solvency dimensions using key financial ratios derived from publicly available annual report. data.
B9: Scope & Methodology
B10: Data sourced from Screener.in (NSE/BSE filings). 10+ financial ratios calculated across 4 categories: Profitability (Net Profit Margin, ROE, ROA, EBITDA Margin), Liquidity (Current Ratio, Quick Ratio), Efficiency (Asset Turnover, Debtor Days) and Solvency (Debt-to-Equity, Interest Coverage). Findings presented through an interactive Excel dashboard.
B12: 02 | Profitability Analysis
B13: Ratio / Metric | C13: Insight & Analysis
B14: Net Profit Margin % | C14: The Net Profit Margin% for TCS has been consistently higher in comparison to Infosys. TCS Net Profit Margin% grew from 18.7% to 19.0% while for Infosys it initially grew from 16.4% to 17.1% and then reverted back to 16.4%. Conclusion- This means TCS has been more efficient in its cost control and operations than Infosys. Infosys growth followed by decline suggest possible cost pressures and pricing change. TCS stable and consistent growth indicates its better position to withstand industry headwinds moving forward.
B15: Return on Equity (ROE) % | C15: TCS consistently outperformed Infosys on Return on Equity across all three years. TCS ROE grew from 46.6% to 51.2% which shows its commendable growth in maximising returns to its shareholders which not only increases the market value of the company but also ensures continued trust of the real owners of the company. For Infosys there has been a decline in the ROE from 32.0% to 27.9%, which indicates fall in the returns to the shareholders. Conclusion- TCS consistent growth in ROE surely suggests towards its continued growth and efficiency in using equity. Infosys decline in ROE is possibly due to rising equity base from retained earnings or increasing cost pressures — which may concern long term investors.
B16: Return on Assets (ROA) % | C16: TCS outperformed Infosys in Return on Assets (ROA) across FY23–FY25, indicating stronger efficiency in utilizing assets to generate profits. TCS ROA improved from 29.5% in FY23 to 31.6% in FY24 before slightly declining to 30.6% in FY25, possibly due to rising operating and non-operating expenses. Despite the decline, TCS maintained a relatively strong ROA level. Infosys ROA remained comparatively stable at 19.3% and 19.1% in FY23 and FY24 respectively, before declining to 18.1% in FY25, reflecting comparatively lower asset utilization efficiency. Conclusion – TCS maintained a significantly stronger ROA throughout the period, reflecting better asset utilization and profitability. While both companies witnessed a slight decline in FY25, Infosys’ relatively stable ROA indicates steady — though less efficient — asset management compared to TCS.
B17: EBITDA Margin % | C17: TCS maintained a consistently higher EBITDA margin compared to Infosys during FY23–FY25, reporting an EBITDA margin of approximately 28.5% in FY25 against Infosys’ 27.0%. TCS’ EBITDA margin improved from 28.5% in FY23 to 28.8% in FY24 before moderating slightly in FY25, indicating stable operational profitability despite possible cost pressures. Infosys, on the other hand, demonstrated gradual and consistent improvement in EBITDA margins from 26.8% in FY23 to 27.0% in FY25. This reflects steady operational efficiency and controlled cost growth relative to revenue expansion. Conclusion - Overall, TCS maintained stronger operating profitability than Infosys throughout the analysis period, as reflected by its relatively higher EBITDA margins. However, the margin gap between the two companies remained moderate, indicating stable operational performance and positive long-term growth potential for both firms.
B19: 03 | Liquidity & Efficiency Analysis
B20: Ratio / Metric | C20: Insight & Analysis
B21: Current & Quick Ratio | C21: Both companies show Current Ratio above 1.5 indicating decent liquidity positions of the respective companies. Higher the ratio higher is the ability of the company to meet their short-term obligations. Higher Quick Ratio suggests that the companies liquidity position are not heavily reliant on its inventory which is typical of the sector the firms operate in. Infosys ratio of 2.11 in FY25 is higher than TCS at 1.89 in FY25, this means Infosys is better placed in meeting its short-term debt obligations than TCS is. Nevertheless, though TCS Current and Quick Ration are lower than Infosys but still at a decently higher level. Conclusion: This means both companies are doing well in terms of its liquidity position which not only strengthens financial health but also increases the trust of investors and other key stakeholders.
B22: Asset Turnover Ratio | C22: TCS generates ₹1.61 of revenue per ₹1 of assets vs Infosys at ₹1.10 revenue per ₹1 of assets. This shows that TCS is better positioned in utilising its assets to generate revenues and is more efficient in its resource management. Higher Asset Turnover Ratio of TCS is also reflected in higher Return to Asset%. While Infosys has slightly lower ratio than that of TCS but is still quite efficient in its asset utilisation. Lower ratio is possibly due to lower revenue relative to asset size accompanied by declining ROE trend. Conclusion: TCS has scaled revenue far more efficiently than its asset base has grown, while Infosys's equity and asset base are growing faster than its revenue, compressing its ratio year over year.
B23: Debtor Days | C23: TCS's collection cycle is approximately 14 days longer than Infosys's, indicating that cash remains locked in receivables for a longer period. In contrast, Infosys's 69-day collection period suggests relatively stronger receivables management and faster cash conversion. Conclusion: The rise in debtor days for both companies since FY23 points to a wider industry trend, with clients increasingly seeking extended payment terms in the post-pandemic market.
B25: 04 | Solvency Analysis
B26: Ratio / Metric | C26: Insight & Analysis
B27: Debt to Equity Ratio | C27: TCS has a debt-to-equity ratio of 0.10, meaning it uses very little debt to finance its operations. For a company of its scale, this reflects a highly conservative capital structure and a strong balance sheet. Infosys has further strengthened its position by reducing its debt-to-equity ratio from 0.11 to 0.09. This suggests the company has either been paying down debt, growing its equity base, or both—an encouraging sign of financial discipline. Conclusion: Overall, both companies maintain exceptionally low levels of debt, indicating minimal financial risk from leverage. The difference between the two ratios is marginal and unlikely to be a significant factor in an investor's decision-making process.
B28: Interest Coverage Ratio | C28: TCS generates enough operating profit to cover its interest expenses about 84 times over, and this coverage has improved over the past few years. The increase reflects stronger operating earnings while interest costs have remained relatively stable. Infosys's interest coverage ratio has declined from 123.7× to 94.3×. This drop was largely driven by a temporary rise in interest expenses in FY24, although those costs eased in FY25. Even so, the company still generates more than enough profit to comfortably meet its interest obligations Conclusion: Both companies are in a very strong financial position, with interest coverage levels that indicate virtually no risk in servicing their debt. The more important takeaway is the trend: TCS has shown improvement over time, while Infosys has seen some moderation. However, both remain firmly in a low-risk, financially healthy zone.
B30: Strength- TCS & Infosys
B46: Final Conclusion
B47: Based on the financial trends over the last three years, TCS appears to be the stronger performer in terms of both efficiency and profitability. Its higher and steadily improving ROE, ROCE, profit margins, and asset utilization indicate that the company is generating increasing value from the resources available to it. While TCS does take slightly longer to collect payments from customers and has seen a modest increase in borrowings, these factors remain well within manageable levels and do not currently pose a significant concern. Infosys, on the other hand, continues to be a financially sound and conservatively managed company. However, its recent performance suggests some moderation in operational efficiency. Key indicators such as ROE have gradually declined, profit growth has slowed considerably, and operating expenses have been increasing at a slightly faster pace than revenue. While none of these trends are alarming on their own, they do indicate that the company is facing greater pressure in maintaining its historical levels of profitability. Overall, both companies remain financially strong, but TCS has demonstrated stronger execution and more consistent improvement across key performance metrics. Unless Infosys is able to accelerate revenue growth or improve cost efficiency, the performance gap between the two companies may continue to widen over time. Investment View: TCS stands out as a reliable long-term compounder, backed by improving fundamentals and strong execution. Infosys offers a solid foundation but needs stronger growth or shareholder-friendly initiatives, such as buybacks, to close the gap and improve investor sentiment.
B48: Data Source: Screener.in (NSE/BSE Annual Reports) | Analysis Period: FY2023–FY2025 | Prepared as part of Financial Analyst certification – Udemy
